twAuto/__init__.py
twAuto/twauto.py
twAuto-0.4.0.dist-info/LICENCE.MD
twAuto-0.4.0.dist-info/METADATA
twAuto-0.4.0.dist-info/WHEEL
twAuto-0.4.0.dist-info/top_level.txt
twAuto-0.4.0.dist-info/RECORD
