Metadata-Version: 2.1
Name: twAuto
Version: 0.4.0
Summary: TwAuto is a library for testing your code on pre-Twitter API application stage.
Home-page: https://github.com/EKOzkan/twAuto
Author: Ekin Kagan Ozkan
Author-email: ekinkagan@gmail.com
License: MIT
License-File: LICENCE.MD
Requires-Dist: selenium ==4.4.3
Requires-Dist: bs4
Requires-Dist: webdriver-manager
